spectests/spectests/cli.py
spectests/spectests/decorators/testcase.py
spectests/spectests/http/testclient.py
spectests/spectests/interfaces/specification.py
spectests/spectests/interfaces/spectypes.py
spectests/spectests/provider.py
spectests/spectests/utils/spec_iter.py
ascender_spectests-0.1.0.dist-info/METADATA
ascender_spectests-0.1.0.dist-info/WHEEL
ascender_spectests-0.1.0.dist-info/RECORD
