Metadata-Version: 2.3
Name: ascender-spectests
Version: 0.1.0
Summary: ascender-spectests
Author: Zahcoder34
Author-email: Zakhriw@gmail.com
Requires-Python: >=3.11,<3.14
Classifier: Programming Language :: Python :: 3
Classifier: Programming Language :: Python :: 3.11
Classifier: Programming Language :: Python :: 3.12
Classifier: Programming Language :: Python :: 3.13
Requires-Dist: ascender-framework (>=2.0rc6,<3.0)
